{"items":[{"custitem_ns_pr_item_attributes":"&nbsp;","custitem_kit_builder_bike":false,"custitem_ns_pr_rating":5.0,"isonline":true,"matrixchilditems_detail":[{"isinstock":true,"itemid":"701505213","ispurchasable":true,"stockdescription":"","isbackorderable":true,"custitem_matrix_color":"BLACK","onlinecustomerprice_detail":{"onlinecustomerprice_formatted":"$30.00","onlinecustomerprice":30.0},"custitem_matrix_size":"MD","internalid":89615,"showoutofstockmessage":false,"outofstockbehavior":"- Default -","quantityavailable":211.0,"outofstockmessage":"","pricelevel1":30.0,"pricelevel1_formatted":"$30.00"},{"isinstock":true,"itemid":"701505212","ispurchasable":true,"stockdescription":"","isbackorderable":true,"custitem_matrix_color":"BLACK","onlinecustomerprice_detail":{"onlinecustomerprice_formatted":"$30.00","onlinecustomerprice":30.0},"custitem_matrix_size":"SM","internalid":89614,"showoutofstockmessage":false,"outofstockbehavior":"- Default -","quantityavailable":67.0,"outofstockmessage":"","pricelevel1":30.0,"pricelevel1_formatted":"$30.00"},{"isinstock":true,"itemid":"701505215","ispurchasable":true,"stockdescription":"","isbackorderable":true,"custitem_matrix_color":"BLACK","onlinecustomerprice_detail":{"onlinecustomerprice_formatted":"$30.00","onlinecustomerprice":30.0},"custitem_matrix_size":"XL","internalid":89617,"showoutofstockmessage":false,"outofstockbehavior":"- Default -","quantityavailable":150.0,"outofstockmessage":"","pricelevel1":30.0,"pricelevel1_formatted":"$30.00"},{"isinstock":true,"itemid":"701505214","ispurchasable":true,"stockdescription":"","isbackorderable":true,"custitem_matrix_color":"BLACK","onlinecustomerprice_detail":{"onlinecustomerprice_formatted":"$30.00","onlinecustomerprice":30.0},"custitem_matrix_size":"LG","internalid":89616,"showoutofstockmessage":false,"outofstockbehavior":"- Default -","quantityavailable":207.0,"outofstockmessage":"","pricelevel1":30.0,"pricelevel1_formatted":"$30.00"},{"isinstock":true,"itemid":"701505216","ispurchasable":true,"stockdescription":"","isbackorderable":true,"custitem_matrix_color":"BLACK","onlinecustomerprice_detail":{"onlinecustomerprice_formatted":"$30.00","onlinecustomerprice":30.0},"custitem_matrix_size":"2X","internalid":89618,"showoutofstockmessage":false,"outofstockbehavior":"- Default -","quantityavailable":94.0,"outofstockmessage":"","pricelevel1":30.0,"pricelevel1_formatted":"$30.00"},{"isinstock":true,"itemid":"701505972","ispurchasable":true,"stockdescription":"","isbackorderable":true,"custitem_matrix_color":"CHARCOAL","onlinecustomerprice_detail":{"onlinecustomerprice_formatted":"$30.00","onlinecustomerprice":30.0},"custitem_matrix_size":"SM","internalid":81575,"showoutofstockmessage":false,"outofstockbehavior":"- Default -","quantityavailable":10.0,"outofstockmessage":"","pricelevel1":30.0,"pricelevel1_formatted":"$30.00"},{"isinstock":false,"itemid":"701505974","ispurchasable":true,"stockdescription":"","isbackorderable":true,"custitem_matrix_color":"CHARCOAL","onlinecustomerprice_detail":{"onlinecustomerprice_formatted":"$30.00","onlinecustomerprice":30.0},"custitem_matrix_size":"LG","internalid":81577,"showoutofstockmessage":true,"outofstockbehavior":"- Default -","quantityavailable":0.0,"outofstockmessage":"","pricelevel1":30.0,"pricelevel1_formatted":"$30.00"},{"isinstock":true,"itemid":"701505973","ispurchasable":true,"stockdescription":"","isbackorderable":true,"custitem_matrix_color":"CHARCOAL","onlinecustomerprice_detail":{"onlinecustomerprice_formatted":"$30.00","onlinecustomerprice":30.0},"custitem_matrix_size":"MD","internalid":81576,"showoutofstockmessage":false,"outofstockbehavior":"- Default -","quantityavailable":11.0,"outofstockmessage":"","pricelevel1":30.0,"pricelevel1_formatted":"$30.00"},{"isinstock":true,"itemid":"701505976","ispurchasable":true,"stockdescription":"","isbackorderable":true,"custitem_matrix_color":"CHARCOAL","onlinecustomerprice_detail":{"onlinecustomerprice_formatted":"$30.00","onlinecustomerprice":30.0},"custitem_matrix_size":"2X","internalid":81579,"showoutofstockmessage":false,"outofstockbehavior":"- Default -","quantityavailable":21.0,"outofstockmessage":"","pricelevel1":30.0,"pricelevel1_formatted":"$30.00"},{"isinstock":true,"itemid":"701505975","ispurchasable":true,"stockdescription":"","isbackorderable":true,"custitem_matrix_color":"CHARCOAL","onlinecustomerprice_detail":{"onlinecustomerprice_formatted":"$30.00","onlinecustomerprice":30.0},"custitem_matrix_size":"XL","internalid":81578,"showoutofstockmessage":false,"outofstockbehavior":"- Default -","quantityavailable":7.0,"outofstockmessage":"","pricelevel1":30.0,"pricelevel1_formatted":"$30.00"},{"isinstock":false,"itemid":"701505172","ispurchasable":true,"stockdescription":"","isbackorderable":true,"custitem_matrix_color":"WHITE","onlinecustomerprice_detail":{"onlinecustomerprice_formatted":"$30.00","onlinecustomerprice":30.0},"custitem_matrix_size":"SM","internalid":88111,"showoutofstockmessage":true,"outofstockbehavior":"- Default -","quantityavailable":0.0,"outofstockmessage":"","pricelevel1":30.0,"pricelevel1_formatted":"$30.00"},{"isinstock":false,"itemid":"701505174","ispurchasable":true,"stockdescription":"","isbackorderable":true,"custitem_matrix_color":"WHITE","onlinecustomerprice_detail":{"onlinecustomerprice_formatted":"$30.00","onlinecustomerprice":30.0},"custitem_matrix_size":"LG","internalid":88113,"showoutofstockmessage":true,"outofstockbehavior":"- Default -","quantityavailable":0.0,"outofstockmessage":"","pricelevel1":30.0,"pricelevel1_formatted":"$30.00"},{"isinstock":true,"itemid":"701505173","ispurchasable":true,"stockdescription":"","isbackorderable":true,"custitem_matrix_color":"WHITE","onlinecustomerprice_detail":{"onlinecustomerprice_formatted":"$30.00","onlinecustomerprice":30.0},"custitem_matrix_size":"MD","internalid":88112,"showoutofstockmessage":false,"outofstockbehavior":"- Default -","quantityavailable":10.0,"outofstockmessage":"","pricelevel1":30.0,"pricelevel1_formatted":"$30.00"},{"isinstock":true,"itemid":"701505176","ispurchasable":true,"stockdescription":"","isbackorderable":true,"custitem_matrix_color":"WHITE","onlinecustomerprice_detail":{"onlinecustomerprice_formatted":"$30.00","onlinecustomerprice":30.0},"custitem_matrix_size":"2X","internalid":88115,"showoutofstockmessage":false,"outofstockbehavior":"- Default -","quantityavailable":16.0,"outofstockmessage":"","pricelevel1":30.0,"pricelevel1_formatted":"$30.00"},{"isinstock":false,"itemid":"701505175","ispurchasable":true,"stockdescription":"","isbackorderable":true,"custitem_matrix_color":"WHITE","onlinecustomerprice_detail":{"onlinecustomerprice_formatted":"$30.00","onlinecustomerprice":30.0},"custitem_matrix_size":"XL","internalid":88114,"showoutofstockmessage":true,"outofstockbehavior":"- Default -","quantityavailable":0.0,"outofstockmessage":"","pricelevel1":30.0,"pricelevel1_formatted":"$30.00"},{"isinstock":true,"itemid":"701505373","ispurchasable":true,"stockdescription":"","isbackorderable":true,"custitem_matrix_color":"NAVY","onlinecustomerprice_detail":{"onlinecustomerprice_formatted":"$30.00","onlinecustomerprice":30.0},"custitem_matrix_size":"MD","internalid":88117,"showoutofstockmessage":false,"outofstockbehavior":"- Default -","quantityavailable":62.0,"outofstockmessage":"","pricelevel1":30.0,"pricelevel1_formatted":"$30.00"},{"isinstock":true,"itemid":"701505372","ispurchasable":true,"stockdescription":"","isbackorderable":true,"custitem_matrix_color":"NAVY","onlinecustomerprice_detail":{"onlinecustomerprice_formatted":"$30.00","onlinecustomerprice":30.0},"custitem_matrix_size":"SM","internalid":88116,"showoutofstockmessage":false,"outofstockbehavior":"- Default -","quantityavailable":36.0,"outofstockmessage":"","pricelevel1":30.0,"pricelevel1_formatted":"$30.00"},{"isinstock":true,"itemid":"701505375","ispurchasable":true,"stockdescription":"","isbackorderable":true,"custitem_matrix_color":"NAVY","onlinecustomerprice_detail":{"onlinecustomerprice_formatted":"$30.00","onlinecustomerprice":30.0},"custitem_matrix_size":"XL","internalid":88119,"showoutofstockmessage":false,"outofstockbehavior":"- Default -","quantityavailable":212.0,"outofstockmessage":"","pricelevel1":30.0,"pricelevel1_formatted":"$30.00"},{"isinstock":true,"itemid":"701505374","ispurchasable":true,"stockdescription":"","isbackorderable":true,"custitem_matrix_color":"NAVY","onlinecustomerprice_detail":{"onlinecustomerprice_formatted":"$30.00","onlinecustomerprice":30.0},"custitem_matrix_size":"LG","internalid":88118,"showoutofstockmessage":false,"outofstockbehavior":"- Default -","quantityavailable":157.0,"outofstockmessage":"","pricelevel1":30.0,"pricelevel1_formatted":"$30.00"},{"isinstock":true,"itemid":"701505376","ispurchasable":true,"stockdescription":"","isbackorderable":true,"custitem_matrix_color":"NAVY","onlinecustomerprice_detail":{"onlinecustomerprice_formatted":"$30.00","onlinecustomerprice":30.0},"custitem_matrix_size":"2X","internalid":88120,"showoutofstockmessage":false,"outofstockbehavior":"- Default -","quantityavailable":48.0,"outofstockmessage":"","pricelevel1":30.0,"pricelevel1_formatted":"$30.00"}],"custitem_ns_pr_count":1,"ispurchasable":true,"custitem_ec_note_for_color":"","custitem_ns_pr_attributes_rating":"{}","stockdescription":"","custitem_web_store_features":"<div class=\"container-fluid prd-info\"><div class=\"container\"><div class=\"copy\" style=\"max-width:100%\"><p>100% Cotton ringspun jersey TLD core fit tee with screen-printed artwork on front and TLD pinch label at back bottom edge. </p></div></div></div>","storedetaileddescription":"","itemimages_detail":{"CHARCOAL":{"urls":[{"altimagetext":"","url":"http://www.troyleedesigns.com/images/product/2017-tld-ktm-team-tee_CHARCOAL-1.jpg"},{"altimagetext":"","url":"http://www.troyleedesigns.com/images/product/2017-tld-ktm-team-tee_CHARCOAL-2.jpg"}]},"NAVY":{"urls":[{"altimagetext":"","url":"http://www.troyleedesigns.com/images/product/2017-tld-ktm-team-tee_NAVY-1.jpg"},{"altimagetext":"","url":"http://www.troyleedesigns.com/images/product/2017-tld-ktm-team-tee_NAVY-2.jpg"}]},"WHITE":{"urls":[{"altimagetext":"","url":"http://www.troyleedesigns.com/images/product/2017-tld-ktm-team-tee_WHITE-1.jpg"},{"altimagetext":"","url":"http://www.troyleedesigns.com/images/product/2017-tld-ktm-team-tee_WHITE-2.jpg"}]},"BLACK":{"urls":[{"altimagetext":"","url":"http://www.troyleedesigns.com/images/product/2017-tld-ktm-team-tee_BLACK-1.jpg"},{"altimagetext":"","url":"http://www.troyleedesigns.com/images/product/2017-tld-ktm-team-tee_BLACK-2.jpg"}]}},"custitem_matrix_color":"ANTIQUE BRASS, AQUA SNOW, BLACK, CHARCOAL, NAVY, SILVER, WHITE, WHITE / BLUE","onlinecustomerprice_detail":{"onlinecustomerprice_formatted":"$30.00","onlinecustomerprice":30.0},"custitem_tld_prodline":"TEES/TANKS","custitem_ns_pr_rating_by_rate":"{\"5\":\"1\"}","pricelevel5_formatted":"$30.00","internalid":81422,"featureddescription":"","itemoptions_detail":{"matrixtype":"parent","fields":[{"ismandatory":true,"internalid":"custcol_matrix_color","ismatrixdimension":true,"values":[{"label":"- Select -"},{"internalid":"7","label":"BLACK"},{"internalid":"35","label":"CHARCOAL"},{"internalid":"92","label":"NAVY"},{"internalid":"126","label":"WHITE"}],"label":"Color:","type":"select","sourcefrom":"custitem_matrix_color"},{"ismandatory":true,"internalid":"custcol_matrix_size","ismatrixdimension":true,"values":[{"label":"- Select -"},{"internalid":"52","label":"SM"},{"internalid":"49","label":"MD"},{"internalid":"47","label":"LG"},{"internalid":"54","label":"XL"},{"internalid":"16","label":"2X"}],"label":"Size:","type":"select","sourcefrom":"custitem_matrix_size"},{"internalid":"custcol_jerseyname","label":"Name","type":"text"},{"internalid":"custcol_jerseynumber","label":"Number","type":"text"}]},"outofstockmessage":"Out of stock","relateditemsdescription":"","storedescription":"","pricelevel1_formatted":"$30.00","isinactive":false,"isinstock":true,"metataghtml":"<meta name=\"description\" content=\"Shop 2017 Team TLD KTM Tee at TLD Troy Lee Designs Official\"/>","pagetitle2":"2017 Team TLD KTM Tee | Troy Lee Designs®","relateditems_detail":[],"itemid":"701505","custitem_kit_builder_moto":false,"defaultcategory_detail":[{"label":"home","url":"home"},{"label":"sportswear","url":""},{"label":"collaborations","url":""},{"label":"KTM","url":"ktm"}],"isbackorderable":true,"custitem_cale_item":false,"custitem_matrix_size":"SM, MD, LG, XL, 2X, 18, 11-13, 12, 18\", 2\"","storedescription2":"(PM) CORE TEES / TANKS ; 2017 TLD KTM TEAM","showoutofstockmessage":false,"outofstockbehavior":"Allow back orders but display out-of-stock message","itemtype":"InvtPart","quantityavailable":1319.0,"pricelevel5":30.0,"custitem_mips_item":false,"displayname":"(PM) CORE TEES / TANKS ; 2017 TLD KTM TEAM","storedisplayname2":"2017 Team TLD KTM Tee","pricelevel1":30.0,"pagetitle":"2017 Team TLD KTM Tee | Troy Lee Designs®","urlcomponent":"2017-tld-ktm-team-tee","custitem_ec_note_for_size":""}],"facets":[{"id":"custitem_featured_items_general","url":"custitem_featured_items_general","values":[{"url":"false"}]},{"id":"custitem_featured_items_moto","url":"custitem_featured_items_moto","values":[{"url":"true"}]},{"id":"custitem_kit_builder_bike","url":"custitem_kit_builder_bike","values":[{"url":"false"}]},{"id":"custitem_kit_builder_moto","url":"custitem_kit_builder_moto","values":[{"url":"false"}]},{"id":"custitem_matrix_color","url":"color","values":[{"url":"BLACK","label":"BLACK"},{"url":"CHARCOAL","label":"CHARCOAL"},{"url":"NAVY","label":"NAVY"},{"url":"WHITE","label":"WHITE"}]},{"id":"custitem_matrix_size","url":"size","values":[{"url":"SM","label":"SM"},{"url":"MD","label":"MD"},{"url":"LG","label":"LG"},{"url":"XL","label":"XL"},{"url":"2X","label":"2X"}]},{"id":"custitem_pro_setup_bike","url":"custitem_pro_setup_bike","values":[{"url":"false"}]},{"id":"custitem_pro_setup_moto","url":"custitem_pro_setup_moto","values":[{"url":"false"}]},{"id":"onlinecustomerprice","url":"price","values":[{"url":"30.0","label":"30.0"}],"min":30.0,"max":30.0,"ranges":[]},{"id":"category","values":[{"url":"home","id":"home","values":[{"url":"sportswear","id":"home/sportswear","values":[{"url":"men","id":"home/sportswear/men","values":[{"url":"t-shirts & tops","id":"home/sportswear/men/t-shirts","values":[]}]},{"url":"collaborations","id":"home/sportswear/collaborations","values":[{"url":"KTM","id":"home/sportswear/collaborations/ktm","values":[]}]}]}]}]}],"corrections":[],"locale":{"country":"US","language":"en","currency":"USD","region":1},"volatility":"short","code":200,"warnings":{}}