{"items":[{"custitem_ns_pr_item_attributes":"&nbsp;","custitem_kit_builder_bike":false,"custitem_ns_pr_rating":5.0,"isonline":true,"matrixchilditems_detail":[{"isinstock":true,"itemid":"406003014","ispurchasable":true,"stockdescription":"","isbackorderable":false,"custitem_matrix_color":"FLO PINK","onlinecustomerprice_detail":{"onlinecustomerprice_formatted":"$22.00","onlinecustomerprice":22.0},"custitem_matrix_size":"LG","internalid":60809,"showoutofstockmessage":false,"outofstockbehavior":"- Default -","quantityavailable":15.0,"outofstockmessage":"","pricelevel1":22.0,"pricelevel1_formatted":"$22.00"},{"isinstock":true,"itemid":"406003015","ispurchasable":true,"stockdescription":"","isbackorderable":false,"custitem_matrix_color":"FLO PINK","onlinecustomerprice_detail":{"onlinecustomerprice_formatted":"$22.00","onlinecustomerprice":22.0},"custitem_matrix_size":"XL","internalid":60810,"showoutofstockmessage":false,"outofstockbehavior":"- Default -","quantityavailable":48.0,"outofstockmessage":"","pricelevel1":22.0,"pricelevel1_formatted":"$22.00"},{"isinstock":true,"itemid":"406003221","ispurchasable":true,"stockdescription":"","isbackorderable":false,"custitem_matrix_color":"BLACK / BLACK","onlinecustomerprice_detail":{"onlinecustomerprice_formatted":"$22.00","onlinecustomerprice":22.0},"custitem_matrix_size":"XS","internalid":60821,"showoutofstockmessage":false,"outofstockbehavior":"- Default -","quantityavailable":169.0,"outofstockmessage":"","pricelevel1":22.0,"pricelevel1_formatted":"$22.00"},{"isinstock":true,"itemid":"406003222","ispurchasable":true,"stockdescription":"","isbackorderable":false,"custitem_matrix_color":"BLACK / BLACK","onlinecustomerprice_detail":{"onlinecustomerprice_formatted":"$22.00","onlinecustomerprice":22.0},"custitem_matrix_size":"SM","internalid":60822,"showoutofstockmessage":false,"outofstockbehavior":"- Default -","quantityavailable":277.0,"outofstockmessage":"","pricelevel1":22.0,"pricelevel1_formatted":"$22.00"},{"isinstock":true,"itemid":"406003223","ispurchasable":true,"stockdescription":"","isbackorderable":false,"custitem_matrix_color":"BLACK / BLACK","onlinecustomerprice_detail":{"onlinecustomerprice_formatted":"$22.00","onlinecustomerprice":22.0},"custitem_matrix_size":"MD","internalid":60823,"showoutofstockmessage":false,"outofstockbehavior":"- Default -","quantityavailable":294.0,"outofstockmessage":"","pricelevel1":22.0,"pricelevel1_formatted":"$22.00"},{"isinstock":true,"itemid":"406003224","ispurchasable":true,"stockdescription":"","isbackorderable":false,"custitem_matrix_color":"BLACK / BLACK","onlinecustomerprice_detail":{"onlinecustomerprice_formatted":"$22.00","onlinecustomerprice":22.0},"custitem_matrix_size":"LG","internalid":60824,"showoutofstockmessage":false,"outofstockbehavior":"- Default -","quantityavailable":453.0,"outofstockmessage":"","pricelevel1":22.0,"pricelevel1_formatted":"$22.00"},{"isinstock":true,"itemid":"406003225","ispurchasable":true,"stockdescription":"","isbackorderable":false,"custitem_matrix_color":"BLACK / BLACK","onlinecustomerprice_detail":{"onlinecustomerprice_formatted":"$22.00","onlinecustomerprice":22.0},"custitem_matrix_size":"XL","internalid":60825,"showoutofstockmessage":false,"outofstockbehavior":"- Default -","quantityavailable":494.0,"outofstockmessage":"","pricelevel1":22.0,"pricelevel1_formatted":"$22.00"},{"isinstock":true,"itemid":"406003334","ispurchasable":true,"stockdescription":"","isbackorderable":false,"custitem_matrix_color":"LIGHT BLUE","onlinecustomerprice_detail":{"onlinecustomerprice_formatted":"$22.00","onlinecustomerprice":22.0},"custitem_matrix_size":"LG","internalid":60829,"showoutofstockmessage":false,"outofstockbehavior":"- Default -","quantityavailable":13.0,"outofstockmessage":"","pricelevel1":22.0,"pricelevel1_formatted":"$22.00"},{"isinstock":true,"itemid":"406003335","ispurchasable":true,"stockdescription":"","isbackorderable":false,"custitem_matrix_color":"LIGHT BLUE","onlinecustomerprice_detail":{"onlinecustomerprice_formatted":"$22.00","onlinecustomerprice":22.0},"custitem_matrix_size":"XL","internalid":60830,"showoutofstockmessage":false,"outofstockbehavior":"- Default -","quantityavailable":23.0,"outofstockmessage":"","pricelevel1":22.0,"pricelevel1_formatted":"$22.00"},{"isinstock":true,"itemid":"406003445","ispurchasable":true,"stockdescription":"","isbackorderable":false,"custitem_matrix_color":"RED / RED","onlinecustomerprice_detail":{"onlinecustomerprice_formatted":"$22.00","onlinecustomerprice":22.0},"custitem_matrix_size":"XL","internalid":60840,"showoutofstockmessage":false,"outofstockbehavior":"- Default -","quantityavailable":45.0,"outofstockmessage":"","pricelevel1":22.0,"pricelevel1_formatted":"$22.00"},{"isinstock":true,"itemid":"406003551","ispurchasable":true,"stockdescription":"","isbackorderable":false,"custitem_matrix_color":"FLO YELLOW","onlinecustomerprice_detail":{"onlinecustomerprice_formatted":"$22.00","onlinecustomerprice":22.0},"custitem_matrix_size":"XS","internalid":60846,"showoutofstockmessage":false,"outofstockbehavior":"- Default -","quantityavailable":164.0,"outofstockmessage":"","pricelevel1":22.0,"pricelevel1_formatted":"$22.00"},{"isinstock":true,"itemid":"406003552","ispurchasable":true,"stockdescription":"","isbackorderable":false,"custitem_matrix_color":"FLO YELLOW","onlinecustomerprice_detail":{"onlinecustomerprice_formatted":"$22.00","onlinecustomerprice":22.0},"custitem_matrix_size":"SM","internalid":60847,"showoutofstockmessage":false,"outofstockbehavior":"- Default -","quantityavailable":180.0,"outofstockmessage":"","pricelevel1":22.0,"pricelevel1_formatted":"$22.00"},{"isinstock":true,"itemid":"406003553","ispurchasable":true,"stockdescription":"","isbackorderable":false,"custitem_matrix_color":"FLO YELLOW","onlinecustomerprice_detail":{"onlinecustomerprice_formatted":"$22.00","onlinecustomerprice":22.0},"custitem_matrix_size":"MD","internalid":60848,"showoutofstockmessage":false,"outofstockbehavior":"- Default -","quantityavailable":116.0,"outofstockmessage":"","pricelevel1":22.0,"pricelevel1_formatted":"$22.00"},{"isinstock":true,"itemid":"406003554","ispurchasable":true,"stockdescription":"","isbackorderable":false,"custitem_matrix_color":"FLO YELLOW","onlinecustomerprice_detail":{"onlinecustomerprice_formatted":"$22.00","onlinecustomerprice":22.0},"custitem_matrix_size":"LG","internalid":60849,"showoutofstockmessage":false,"outofstockbehavior":"- Default -","quantityavailable":204.0,"outofstockmessage":"","pricelevel1":22.0,"pricelevel1_formatted":"$22.00"},{"isinstock":true,"itemid":"406003555","ispurchasable":true,"stockdescription":"","isbackorderable":false,"custitem_matrix_color":"FLO YELLOW","onlinecustomerprice_detail":{"onlinecustomerprice_formatted":"$22.00","onlinecustomerprice":22.0},"custitem_matrix_size":"XL","internalid":60850,"showoutofstockmessage":false,"outofstockbehavior":"- Default -","quantityavailable":300.0,"outofstockmessage":"","pricelevel1":22.0,"pricelevel1_formatted":"$22.00"},{"isinstock":true,"itemid":"406003771","ispurchasable":true,"stockdescription":"","isbackorderable":false,"custitem_matrix_color":"FLO ORANGE","onlinecustomerprice_detail":{"onlinecustomerprice_formatted":"$22.00","onlinecustomerprice":22.0},"custitem_matrix_size":"XS","internalid":60856,"showoutofstockmessage":false,"outofstockbehavior":"- Default -","quantityavailable":35.0,"outofstockmessage":"","pricelevel1":22.0,"pricelevel1_formatted":"$22.00"},{"isinstock":true,"itemid":"406003774","ispurchasable":true,"stockdescription":"","isbackorderable":false,"custitem_matrix_color":"FLO ORANGE","onlinecustomerprice_detail":{"onlinecustomerprice_formatted":"$22.00","onlinecustomerprice":22.0},"custitem_matrix_size":"LG","internalid":60859,"showoutofstockmessage":false,"outofstockbehavior":"- Default -","quantityavailable":57.0,"outofstockmessage":"","pricelevel1":22.0,"pricelevel1_formatted":"$22.00"},{"isinstock":true,"itemid":"406003775","ispurchasable":true,"stockdescription":"","isbackorderable":false,"custitem_matrix_color":"FLO ORANGE","onlinecustomerprice_detail":{"onlinecustomerprice_formatted":"$22.00","onlinecustomerprice":22.0},"custitem_matrix_size":"XL","internalid":60860,"showoutofstockmessage":false,"outofstockbehavior":"- Default -","quantityavailable":102.0,"outofstockmessage":"","pricelevel1":22.0,"pricelevel1_formatted":"$22.00"},{"isinstock":true,"itemid":"406003882","ispurchasable":true,"stockdescription":"","isbackorderable":false,"custitem_matrix_color":"FLO GREEN","onlinecustomerprice_detail":{"onlinecustomerprice_formatted":"$22.00","onlinecustomerprice":22.0},"custitem_matrix_size":"SM","internalid":60862,"showoutofstockmessage":false,"outofstockbehavior":"- Default -","quantityavailable":15.0,"outofstockmessage":"","pricelevel1":22.0,"pricelevel1_formatted":"$22.00"},{"isinstock":true,"itemid":"406003883","ispurchasable":true,"stockdescription":"","isbackorderable":false,"custitem_matrix_color":"FLO GREEN","onlinecustomerprice_detail":{"onlinecustomerprice_formatted":"$22.00","onlinecustomerprice":22.0},"custitem_matrix_size":"MD","internalid":60863,"showoutofstockmessage":false,"outofstockbehavior":"- Default -","quantityavailable":15.0,"outofstockmessage":"","pricelevel1":22.0,"pricelevel1_formatted":"$22.00"},{"isinstock":true,"itemid":"406003884","ispurchasable":true,"stockdescription":"","isbackorderable":false,"custitem_matrix_color":"FLO GREEN","onlinecustomerprice_detail":{"onlinecustomerprice_formatted":"$22.00","onlinecustomerprice":22.0},"custitem_matrix_size":"LG","internalid":60864,"showoutofstockmessage":false,"outofstockbehavior":"- Default -","quantityavailable":66.0,"outofstockmessage":"","pricelevel1":22.0,"pricelevel1_formatted":"$22.00"},{"isinstock":true,"itemid":"406003885","ispurchasable":true,"stockdescription":"","isbackorderable":false,"custitem_matrix_color":"FLO GREEN","onlinecustomerprice_detail":{"onlinecustomerprice_formatted":"$22.00","onlinecustomerprice":22.0},"custitem_matrix_size":"XL","internalid":60865,"showoutofstockmessage":false,"outofstockbehavior":"- Default -","quantityavailable":24.0,"outofstockmessage":"","pricelevel1":22.0,"pricelevel1_formatted":"$22.00"}],"custitem_ns_pr_count":1,"ispurchasable":true,"custitem_ec_note_for_color":"","custitem_ns_pr_attributes_rating":"{}","stockdescription":"","custitem_web_store_features":"<div class=\"container-fluid prd-info\"> <div class=\"container\"> <div class=\"copy\" style=\"max-width:100%\"> <h2>VENTILATED &amp; LIGHTWEIGHT GLOVES</h2> <p><span class=\"lead\">Troy Lee Designs gloves are all researched, designed and meticulously tested</span> before they make their way on to the hands of great athletes around the world. Our acute attention to detail paired with a fearless sense of style and design make for a superior quality product. With a vast selection of colors, construction and levels of protection, there is a perfect fit for every individual. </p> <h6>SE Glove Features:</h6> <ul> <li>Self dyed 2-way stretch spandex body</li> <li>Dual layer perforated Clarino¬ synthetic leather palm</li> <li>Sonic-welded TPR graphics on top of hand and fingers</li> <li>Velcro wrist closure</li> </ul> </div> </div> </div>","storedetaileddescription":"","itemimages_detail":{"WHITE":{"urls":[{"altimagetext":"","url":"http://www.troyleedesigns.com/images/product/air-youth-glove_WHITE-1.jpg"},{"altimagetext":"","url":"http://www.troyleedesigns.com/images/product/air-youth-glove_WHITE-2.jpg"}]},"LIGHTBLUE":{"urls":[{"altimagetext":"","url":"http://www.troyleedesigns.com/images/product/air-youth-glove_LIGHTBLUE-1.jpg"},{"altimagetext":"","url":"http://www.troyleedesigns.com/images/product/air-youth-glove_LIGHTBLUE-2.jpg"}]},"BLACKBLACK":{"urls":[{"altimagetext":"","url":"http://www.troyleedesigns.com/images/product/air-youth-glove_BLACKBLACK-1.jpg"},{"altimagetext":"","url":"http://www.troyleedesigns.com/images/product/air-youth-glove_BLACKBLACK-2.jpg"}]},"RED":{"urls":[{"altimagetext":"","url":"http://www.troyleedesigns.com/images/product/air-youth-glove_RED-1.jpg"},{"altimagetext":"","url":"http://www.troyleedesigns.com/images/product/air-youth-glove_RED-2.jpg"}]},"FLOGREEN":{"urls":[{"altimagetext":"","url":"http://www.troyleedesigns.com/images/product/air-youth-glove_FLOGREEN-1.jpg"},{"altimagetext":"","url":"http://www.troyleedesigns.com/images/product/air-youth-glove_FLOGREEN-2.jpg"}]},"PINK":{"urls":[{"altimagetext":"","url":"http://www.troyleedesigns.com/images/product/air-youth-glove_PINK-1.jpg"},{"altimagetext":"","url":"http://www.troyleedesigns.com/images/product/air-youth-glove_PINK-2.jpg"}]},"FLOYELLOW":{"urls":[{"altimagetext":"","url":"http://www.troyleedesigns.com/images/product/air-youth-glove_FLOYELLOW-1.jpg"},{"altimagetext":"","url":"http://www.troyleedesigns.com/images/product/air-youth-glove_FLOYELLOW-2.jpg"}]},"REDRED":{"urls":[{"altimagetext":"","url":"http://www.troyleedesigns.com/images/product/air-youth-glove_REDRED-1.jpg"},{"altimagetext":"","url":"http://www.troyleedesigns.com/images/product/air-youth-glove_REDRED-2.jpg"}]},"BLACK":{"urls":[{"altimagetext":"","url":"http://www.troyleedesigns.com/images/product/air-youth-glove_BLACK-1.jpg"},{"altimagetext":"","url":"http://www.troyleedesigns.com/images/product/air-youth-glove_BLACK-2.jpg"}]},"FLOORANGE":{"urls":[{"altimagetext":"","url":"http://www.troyleedesigns.com/images/product/air-youth-glove_FLOORANGE-1.jpg"},{"altimagetext":"","url":"http://www.troyleedesigns.com/images/product/air-youth-glove_FLOORANGE-2.jpg"}]},"YELLOW":{"urls":[{"altimagetext":"","url":"http://www.troyleedesigns.com/images/product/air-youth-glove_YELLOW-1.jpg"},{"altimagetext":"","url":"http://www.troyleedesigns.com/images/product/air-youth-glove_YELLOW-2.jpg"}]},"FLOPINK":{"urls":[{"altimagetext":"","url":"http://www.troyleedesigns.com/images/product/air-youth-glove_FLOPINK-1.jpg"},{"altimagetext":"","url":"http://www.troyleedesigns.com/images/product/air-youth-glove_FLOPINK-2.jpg"}]},"ORANGE":{"urls":[{"altimagetext":"","url":"http://www.troyleedesigns.com/images/product/air-youth-glove_ORANGE-1.jpg"},{"altimagetext":"","url":"http://www.troyleedesigns.com/images/product/air-youth-glove_ORANGE-2.jpg"}]}},"custitem_matrix_color":"BLACK, BLACK / BLACK, FLO GREEN, FLO ORANGE, FLO PINK, FLO YELLOW, LIGHT BLUE, ORANGE, ORANGE / BLACK, PINK, RED, RED / RED, WHITE, YELLOW","onlinecustomerprice_detail":{"onlinecustomerprice_formatted":"$13.20","onlinecustomerprice":13.2},"custitem_tld_prodline":"GLOVES","custitem_ns_pr_rating_by_rate":"{\"5\":\"1\"}","pricelevel5_formatted":"$22.00","internalid":60800,"featureddescription":"","itemoptions_detail":{"matrixtype":"parent","fields":[{"ismandatory":true,"internalid":"custcol_matrix_color","ismatrixdimension":true,"values":[{"label":"- Select -"},{"internalid":"9","label":"BLACK / BLACK"},{"internalid":"45","label":"FLO GREEN"},{"internalid":"46","label":"FLO ORANGE"},{"internalid":"47","label":"FLO PINK"},{"internalid":"49","label":"FLO YELLOW"},{"internalid":"82","label":"LIGHT BLUE"},{"internalid":"109","label":"RED / RED"},{"internalid":"126","label":"WHITE"}],"label":"Color:","type":"select","sourcefrom":"custitem_matrix_color"},{"ismandatory":true,"internalid":"custcol_matrix_size","ismatrixdimension":true,"values":[{"label":"- Select -"},{"internalid":"56","label":"XS"},{"internalid":"52","label":"SM"},{"internalid":"49","label":"MD"},{"internalid":"47","label":"LG"},{"internalid":"54","label":"XL"}],"label":"Size:","type":"select","sourcefrom":"custitem_matrix_size"},{"internalid":"custcol_jerseyname","label":"Name","type":"text"},{"internalid":"custcol_jerseynumber","label":"Number","type":"text"}]},"outofstockmessage":"Sorry, out of stock.","relateditemsdescription":"","storedescription":"","pricelevel1_formatted":"$22.00","custitem_sort_order":406.0,"isinactive":false,"isinstock":true,"metataghtml":"<meta name=\"description\" content=\"Shop Air Youth Glove at TLD Troy Lee Designs Official\"/>","pagetitle2":"Air Youth Glove | Troy Lee Designs®","relateditems_detail":[],"itemid":"406003","custitem_kit_builder_moto":false,"defaultcategory_detail":[{"label":"home","url":"home"},{"label":"moto","url":""},{"label":"youth","url":""}],"isbackorderable":false,"custitem_sort_order_formatted":"$406.00","custitem_cale_item":false,"custitem_matrix_size":"XXS, XS, SM, MD, LG, XL","storedescription2":"(PM) AIR YOUTH GLOVE ; SOLID","showoutofstockmessage":false,"outofstockbehavior":"Remove item when out-of-stock","itemtype":"InvtPart","quantityavailable":3109.0,"pricelevel5":22.0,"custitem_mips_item":false,"displayname":"(PM) AIR YOUTH GLOVE ; SOLID","storedisplayname2":"Air Youth Glove","pricelevel1":22.0,"pagetitle":"Air Youth Glove | Troy Lee Designs®","urlcomponent":"air-youth-glove","custitem_ec_note_for_size":""}],"facets":[{"id":"custitem_featured_items_general","url":"custitem_featured_items_general","values":[{"url":"false"}]},{"id":"custitem_featured_items_moto","url":"custitem_featured_items_moto","values":[{"url":"false"}]},{"id":"custitem_kit_builder_bike","url":"custitem_kit_builder_bike","values":[{"url":"false"}]},{"id":"custitem_kit_builder_moto","url":"custitem_kit_builder_moto","values":[{"url":"false"}]},{"id":"custitem_matrix_color","url":"color","values":[{"url":"BLACK--SLASH--BLACK","label":"BLACK / BLACK"},{"url":"FLO-GREEN","label":"FLO GREEN"},{"url":"FLO-ORANGE","label":"FLO ORANGE"},{"url":"FLO-PINK","label":"FLO PINK"},{"url":"FLO-YELLOW","label":"FLO YELLOW"},{"url":"LIGHT-BLUE","label":"LIGHT BLUE"},{"url":"RED--SLASH--RED","label":"RED / RED"}]},{"id":"custitem_matrix_size","url":"size","values":[{"url":"XS","label":"XS"},{"url":"SM","label":"SM"},{"url":"MD","label":"MD"},{"url":"LG","label":"LG"},{"url":"XL","label":"XL"}]},{"id":"custitem_pro_setup_bike","url":"custitem_pro_setup_bike","values":[{"url":"false"}]},{"id":"custitem_pro_setup_moto","url":"custitem_pro_setup_moto","values":[{"url":"false"}]},{"id":"onlinecustomerprice","url":"price","values":[{"url":"22.0","label":"22.0"}],"min":22.0,"max":22.0,"ranges":[]},{"id":"category","values":[{"url":"home","id":"home","values":[{"url":"bike","id":"home/bike","values":[{"url":"gloves","id":"home/bike/gloves","values":[]}]},{"url":"moto","id":"home/moto","values":[{"url":"youth","id":"home/moto/youth","values":[]}]}]}]}],"corrections":[],"locale":{"country":"US","language":"en","currency":"USD","region":1},"volatility":"short","code":200,"warnings":{}}